Lab2-SigGen-main/rom.sv
module rom #(
    parameter ADDRESS_WIDTH = 8,
    parameter DATA_WIDTH = 8
)(
    input logic clk,
    input logic [ADDRESS_WIDTH-1:0] addr,
    output logic [DATA_WIDTH-1:0] dout
);

logic [DATA_WIDTH-1:0] rom_array [2**ADDRESS_WIDTH-1:0];

initial begin
    $display("Loading rom.");
    $readmemh("sinerom.mem", rom_array);
end;

always_ff @(posedge clk) begin
    // output is synchronous
    dout <= rom_array[addr];
end

endmodule

Lab2-SigGen-main/task1/counter.sv
module counter #(

    parameter WIDTH = 8
)(

input logic     clk,
input logic     rst,
input logic     en,
input logic [WIDTH-1:0] incr,
output logic[WIDTH-1:0] count

);

always_ff @ (posedge clk)
    if (rst) count <= {WIDTH{1'b0}};
    else count <= count + incr;

endmodule

Lab2-SigGen-main/sinegen.sv
module sinegen #(
    parameter A_WIDTH = 8,
              D_WIDTH = 8
)(
    // interface signals
    input  logic           clk,   // clock
    input  logic           rst,   // reset
    input  logic           en,    // enable
    input  logic [D_WIDTH-1:0] incr, // increment for addr counter
    output logic [D_WIDTH-1:0] dout  // output data
);

    logic [A_WIDTH-1:0] address;  // interconnect wire

    counter addrCounter (
        .clk (clk),
        .rst (rst),
        .en  (en),
        .incr(incr),
        .count(address)
    );

    rom sineRom (
        .clk  (clk),
        .addr (address),
        .dout (dout)
    );

endmodule

Lab2-SigGen-main/sinegen.vcd
$version Generated by VerilatedVcd $end
$date Thu Oct 24 11:04:15 2024 $end
$timescale 1ps $end

 $scope module TOP $end
  $var wire  1 # clk $end
  $var wire  8 ' dout [7:0] $end
  $var wire  1 % en $end
  $var wire  8 & incr [7:0] $end
  $var wire  1 $ rst $end
  $scope module sinegen $end
   $var wire 32 ) A_WIDTH [31:0] $end
   $var wire 32 ) D_WIDTH [31:0] $end
   $var wire  8 ( address [7:0] $end
   $var wire  1 # clk $end
   $var wire  8 ' dout [7:0] $end
   $var wire  1 % en $end
   $var wire  8 & incr [7:0] $end
   $var wire  1 $ rst $end
   $scope module addrCounter $end
    $var wire 32 ) WIDTH [31:0] $end
    $var wire  1 # clk $end
    $var wire  8 ( count [7:0] $end
    $var wire  1 % en $end
    $var wire  8 & incr [7:0] $end
    $var wire  1 $ rst $end
   $upscope $end
   $scope module sineRom $end
    $var wire 32 ) ADDRESS_WIDTH [31:0] $end
    $var wire 32 ) DATA_WIDTH [31:0] $end
    $var wire  8 ( addr [7:0] $end
    $var wire  1 # clk $end
    $var wire  8 ' dout [7:0] $end
   $upscope $end
  $upscope $end
 $upscope $end
$enddefinitions $end


#0
1#
0$
1%
b00000001 &
b00000000 '
b00000000 (
b00000000000000000000000000001000 )
#1
0#
#2
1#
b00110011 &
b11111110 '
b00000001 (
#3
0#
#4
1#
b11111101 '
b00110100 (
#5
0#
#6
1#
b10100011 '
b01100111 (
#7
0#
#8
1#
b00010111 '
b10011010 (
#9
0#
#10
1#
b00011000 '
b11001101 (
#11
0#
#12
1#
b10100110 '
b00000000 (
#13
0#
#14
1#
b11111110 '
b00110011 (
#15
0#
#16
1#
b10100110 '
b01100110 (
#17
0#
#18
1#
b00011000 '
b10011001 (
#19
0#
#20
1#
b00010111 '
b11001100 (
#21
0#
#22
1#
b10100011 '
b11111111 (
#23
0#
#24
1#
b11111101 '
b00110010 (
#25
0#
#26
1#
b10101001 '
b01100101 (
#27
0#
#28
1#
b00011010 '
b10011000 (
#29
0#
#30
1#
b00010101 '
b11001011 (
#31
0#
#32
1#
b10100000 '
b11111110 (
#33
0#
#34
1#
b11111101 '
b00110001 (
#35
0#
#36
1#
b10101100 '
b01100100 (
#37
0#
#38
1#
b00011100 '
b10010111 (
#39
0#
#40
1#
b00010011 '
b11001010 (
#41
0#
#42
1#
b10011101 '
b11111101 (
#43
0#
#44
1#
b11111101 '
b00110000 (
#45
0#
#46
1#
b10101111 '
b01100011 (
#47
0#
#48
1#
b00011110 '
b10010110 (
#49
0#
#50
1#
b00010010 '
b11001001 (
#51
0#
#52
1#
b10011010 '
b11111100 (
#53
0#
#54
1#
b11111101 '
b00101111 (
#55
0#
#56
1#
b10110010 '
b01100010 (
#57
0#
#58
1#
b00100000 '
b10010101 (
#59
0#
#60
1#
b00010000 '
b11001000 (
#61
0#
#62
1#
b10010111 '
b11111011 (
#63
0#
#64
1#
b11111101 '
b00101110 (
#65
0#
#66
1#
b10110101 '
b01100001 (
#67
0#
#68
1#
b00100011 '
b10010100 (
#69
0#
#70
1#
b00001110 '
b11000111 (
#71
0#
#72
1#
b10010100 '
b11111010 (
#73
0#
#74
1#
b11111100 '
b00101101 (
#75
0#
#76
1#
b10111000 '
b01100000 (
#77
0#
#78
1#
b00100101 '
b10010011 (
#79
0#
#80
1#
b00001101 '
b11000110 (
#81
0#
#82
1#
b10010001 '
b11111001 (
#83
0#
#84
1#
b11111100 '
b00101100 (
#85
0#
#86
1#
b10111010 '
b01011111 (
#87
0#
#88
1#
b00100111 '
b10010010 (
#89
0#
#90
1#
b00001100 '
b11000101 (
#91
0#
#92
1#
b10001110 '
b11111000 (
#93
0#
#94
1#
b11111011 '
b00101011 (
#95
0#
#96
1#
b10111101 '
b01011110 (
#97
0#
#98
1#
b00101001 '
b10010001 (
#99
0#
#100
1#
b00001010 '
b11000100 (
#101
0#
#102
1#
b10001011 '
b11110111 (
#103
0#
#104
1#
b11111010 '
b00101010 (
#105
0#
#106
1#
b11000000 '
b01011101 (
#107
0#
#108
1#
b00101100 '
b10010000 (
#109
0#
#110
1#
b00001001 '
b11000011 (
#111
0#
#112
1#
b10001000 '
b11110110 (
#113
0#
#114
1#
b11111010 '
b00101001 (
#115
0#
#116
1#
b11000010 '
b01011100 (
#117
0#
#118
1#
b00101110 '
b10001111 (
#119
0#
#120
1#
b00001000 '
b11000010 (
#121
0#
#122
1#
b10000101 '
b11110101 (
#123
0#
#124
1#
b11111001 '
b00101000 (
#125
0#
#126
1#
b11000101 '
b01011011 (
#127
0#
#128
1#
b00110000 '
b10001110 (
#129
0#
#130
1#
b00000111 '
b11000001 (
#131
0#
#132
1#
b10000010 '
b11110100 (
#133
0#
#134
1#
b11111000 '
b00100111 (
#135
0#
#136
1#
b11001000 '
b01011010 (
#137
0#
#138
1#
b00110011 '
b10001101 (
#139
0#
#140
1#
b00000110 '
b11000000 (
#141
0#
#142
1#
b01111111 '
b11110011 (
#143
0#
#144
1#
b11110111 '
b00100110 (
#145
0#
#146
1#
b11001010 '
b01011001 (
#147
0#
#148
1#
b00110101 '
b10001100 (
#149
0#
#150
1#
b00000101 '
b10111111 (
#151
0#
#152
1#
b01111011 '
b11110010 (
#153
0#
#154
1#
b11110110 '
b00100101 (
#155
0#
#156
1#
b11001101 '
b01011000 (
#157
0#
#158
1#
b00111000 '
b10001011 (
#159
0#
#160
1#
b00110010 &
b00000100 '
b10111110 (
#161
0#
#162
1#
b01111000 '
b11110000 (
#163
0#
#164
1#
b11110100 '
b00100010 (
#165
0#
#166
1#
b00110001 &
b11010100 '
b01010100 (
#167
0#
#168
1#
b01000011 '
b10000101 (
#169
0#
#170
1#
b00110000 &
b00000000 '
b10110110 (
#171
0#
#172
1#
b00101111 &
b01100000 '
b11100110 (
#173
0#
#174
1#
b00101110 &
b11100101 '
b00010101 (
#175
0#
#176
1#
b00101101 &
b11101101 '
b01000011 (
#177
0#
#178
1#
b01110101 '
b01110000 (
#179
0#
#180
1#
b00001001 '
b10011101 (
#181
0#
#182
1#
b00011110 '
b11001010 (
#183
0#
#184
1#
b00101100 &
b10011101 '
b11110111 (
#185
0#
#186
1#
b11111010 '
b00100011 (
#187
0#
#188
1#
b11010001 '
b01001111 (
#189
0#
#190
1#
b00101011 &
b01010001 '
b01111011 (
#191
0#
#192
1#
b00000000 '
b10100110 (
#193
0#
#194
1#
b00110011 '
b11010001 (
#195
0#
#196
1#
b00101010 &
b10110010 '
b11111100 (
#197
0#
#198
1#
b11111101 '
b00100110 (
#199
0#
#200
1#
b00101001 &
b11001010 '
b01010000 (
#201
0#
#202
1#
b00101000 &
b01001110 '
b01111001 (
#203
0#
#204
1#
b00100111 &
b00000001 '
b10100001 (
#205
0#
#206
1#
b00100110 &
b00100111 '
b11001000 (
#207
0#
#208
1#
b10010111 '
b11101110 (
#209
0#
#210
1#
b11110001 '
b00010100 (
#211
0#
#212
1#
b00100101 &
b11101111 '
b00111010 (
#213
0#
#214
1#
b10010001 '
b01011111 (
#215
0#
#216
1#
b00100111 '
b10000100 (
#217
0#
#218
1#
b00100100 &
b00000000 '
b10101001 (
#219
0#
#220
1#
b00100000 &
b00111011 '
b11001101 (
#221
0#
#222
1#
b00011110 &
b10100110 '
b11101101 (
#223
0#
#224
1#
b00011101 &
b11110000 '
b00001011 (
#225
0#
#226
1#
b11111001 '
b00101000 (
#227
0#
#228
1#
b11000101 '
b01000101 (
#229
0#
#230
1#
b01101111 '
b01100010 (
#231
0#
#232
1#
b00100000 '
b01111111 (
#233
0#
#234
1#
b00000000 '
b10011100 (
#235
0#
#236
1#
b00011100 '
b10111001 (
#237
0#
#238
1#
b01101001 '
b11010110 (
#239
0#
#240
1#
b11000000 '
b11110011 (
#241
0#
#242
1#
b11110111 '
b00010000 (
#243
0#
#244
1#
b11110100 '
b00101101 (
#245
0#
#246
1#
b10111000 '
b01001010 (
#247
0#
#248
1#
b01100000 '
b01100111 (
#249
0#
#250
1#
b00010111 '
b10000100 (
#251
0#
#252
1#
b00000000 '
b10100001 (
#253
0#
#254
1#
b00100111 '
b10111110 (
#255
0#
#256
1#
b01111000 '
b11011011 (
#257
0#
#258
1#
b11001101 '
b11111000 (
#259
0#
#260
1#
b00011100 &
b11111011 '
b00010101 (
#261
0#
#262
1#
b00011010 &
b11101101 '
b00110001 (
#263
0#
#264
1#
b00011001 &
b10101100 '
b01001011 (
#265
0#
#266
1#
b00010111 &
b01011101 '
b01100100 (
#267
0#
#268
1#
b00010110 &
b00011100 '
b01111011 (
#269
0#
#270
1#
b00010101 &
b00000000 '
b10010001 (
#271
0#
#272
1#
b00010100 &
b00001010 '
b10100110 (
#273
0#
#274
1#
b00110011 '
b10111010 (
#275
0#
#276
1#
b01101100 '
b11001110 (
#277
0#
#278
1#
b10101001 '
b11100010 (
#279
0#
#280
1#
b11011101 '
b11110110 (
#281
0#
#282
1#
b11111010 '
b00001010 (
#283
0#
#284
1#
b00011110 (
#285
0#
#286
1#
b11011101 '
b00110010 (
#287
0#
#288
1#
b10101001 '
b01000110 (
#289
0#
#290
1#
b01101100 '
b01011010 (
#291
0#
#292
1#
b00110011 '
b01101110 (
#293
0#
#294
1#
b00001100 '
b10000010 (
#295
0#
#296
1#
b00000000 '
b10010110 (
#297
0#
#298
1#
b00010011 &
b00010010 '
b10101010 (
#299
0#
#300
1#
b00010000 &
b00111101 '
b10111101 (
#301
0#
#302
1#
b00001111 &
b01110101 '
b11001101 (
#303
0#
#304
1#
b00001100 &
b10100110 '
b11011100 (
#305
0#
#306
1#
b00001011 &
b11001111 '
b11101000 (
#307
0#
#308
1#
b11101000 '
b11110011 (
#309
0#
#310
1#
b11110111 '
b11111110 (
#311
0#
#312
1#
b11111101 '
b00001001 (
#313
0#
#314
1#
b11111010 '
b00010100 (
#315
0#
#316
1#
b11101111 '
b00011111 (
#317
0#
#318
1#
b11011010 '
b00101010 (
#319
0#
#320
1#
b11000000 '
b00110101 (
#321
0#
#322
1#
b10100000 '
b01000000 (
#323
0#
#324
1#
b01111110 '
b01001011 (
#325
0#
#326
1#
b01011101 '
b01010110 (
#327
0#
#328
1#
b00111101 '
b01100001 (
#329
0#
#330
1#
b00100011 '
b01101100 (
#331
0#
#332
1#
b00001110 '
b01110111 (
#333
0#
#334
1#
b00000011 '
b10000010 (
#335
0#
#336
1#
b00001010 &
b00000000 '
b10001101 (
#337
0#
#338
1#
b00001000 &
b00000110 '
b10010111 (
#339
0#
#340
1#
b00000111 &
b00010011 '
b10011111 (
#341
0#
#342
1#
b00000101 &
b00100011 '
b10100110 (
#343
0#
#344
1#
b00000100 &
b00110011 '
b10101011 (
#345
0#
#346
1#
b00000011 &
b01000000 '
b10101111 (
#347
0#
#348
1#
b01001011 '
b10110010 (
#349
0#
#350
1#
b01010100 '
b10110101 (
#351
0#
#352
1#
b01011101 '
b10111000 (
#353
0#
#354
1#
b01100110 '
b10111011 (
#355
0#
#356
1#
b01101111 '
b10111110 (
#357
0#
#358
1#
b01111000 '
b11000001 (
#359
0#
#360
1#
b10000010 '
b11000100 (
#361
0#
#362
1#
b10001011 '
b11000111 (
#363
0#
#364
1#
b10010100 '
b11001010 (
#365
0#
#366
1#
b10011101 '
b11001101 (
#367
0#
#368
1#
b10100110 '
b11010000 (
#369
0#
#370
1#
b10101111 '
b11010011 (
#371
0#
#372
1#
b10111000 '
b11010110 (
#373
0#
#374
1#
b11000000 '
b11011001 (
#375
0#
#376
1#
b11001000 '
b11011100 (
#377
0#
#378
1#
b11001111 '
b11011111 (
#379
0#
#380
1#
b11010110 '
b11100010 (
#381
0#
#382
1#
b11011101 '
b11100101 (
#383
0#
#384
1#
b11100011 '
b11101000 (
#385
0#
#386
1#
b11101000 '
b11101011 (
#387
0#
#388
1#
b11101101 '
b11101110 (
#389
0#
#390
1#
b11110001 '
b11110001 (
#391
0#
#392
1#
b11110101 '
b11110100 (
#393
0#
#394
1#
b11111000 '
b11110111 (
#395
0#
#396
1#
b11111010 '
b11111010 (
#397
0#
#398
1#
b11111100 '
b11111101 (
#399
0#
#400
1#
b11111101 '
b00000000 (
#401
0#
#402
1#
b11111110 '
b00000011 (
#403
0#
#404
1#
b11111101 '
b00000110 (
#405
0#
#406
1#
b11111100 '
b00001001 (
#407
0#
#408
1#
b00000010 &
b11111010 '
b00001100 (
#409
0#
#410
1#
b11111000 '
b00001110 (
#411
0#
#412
1#
b11110110 '
b00010000 (
#413
0#
#414
1#
b11110100 '
b00010010 (
#415
0#
#416
1#
b11110001 '
b00010100 (
#417
0#
#418
1#
b11101111 '
b00010110 (
#419
0#
#420
1#
b00000001 &
b11101011 '
b00011000 (
#421
0#
#422
1#
b11101000 '
b00011001 (
#423
0#
#424
1#
b11100110 '
b00011010 (
#425
0#
#426
1#
b00000000 &
b11100101 '
b00011011 (
#427
0#
#428
1#
b11100011 '
